airflow_tm1/__init__.py
airflow_tm1/hooks/__init__.py
airflow_tm1/hooks/tm1.py
airflow_tm1/operators/__init__.py
airflow_tm1/operators/tm1_run_chore.py
airflow_tm1/operators/tm1_run_ti.py
airflow_tm1/sensors/__init__.py
airflow_tm1/sensors/tm1_cell_value.py
airflow_tm1/sensors/tm1_element.py
tests/__init__.py
tests/hooks/__init__.py
tests/hooks/test_tm1.py
tests/operators/__init__.py
tests/sensors/__init__.py
airflow_tm1-0.0.13.dist-info/LICENSE
airflow_tm1-0.0.13.dist-info/METADATA
airflow_tm1-0.0.13.dist-info/WHEEL
airflow_tm1-0.0.13.dist-info/top_level.txt
airflow_tm1-0.0.13.dist-info/RECORD
