Metadata-Version: 2.1
Name: airflow-tm1
Version: 0.0.13
Summary: A package to simplify connecting to the TM1 REST API from Apache Airflow
Home-page: https://github.com/scrambldchannel/airflow-tm1
Author: Alexander Sutcliffe
Author-email: sutcliffe.alex@gmail.com
Classifier: Development Status :: 4 - Beta
Classifier: Intended Audience :: Developers
Classifier: Programming Language :: Python :: 3
Classifier: License :: OSI Approved :: Apache Software License
Classifier: Operating System :: OS Independent
Requires-Python: >=3.6
License-File: LICENSE
Requires-Dist: apache-airflow
Requires-Dist: TM1py
Provides-Extra: devel
Requires-Dist: pre-commit ; extra == 'devel'
